ecjtu_wechat_api/__init__.py
ecjtu_wechat_api/main.py
ecjtu_wechat_api/api/__init__.py
ecjtu_wechat_api/api/routes/__init__.py
ecjtu_wechat_api/api/routes/courses.py
ecjtu_wechat_api/api/routes/exams.py
ecjtu_wechat_api/api/routes/scores.py
ecjtu_wechat_api/core/__init__.py
ecjtu_wechat_api/core/config.py
ecjtu_wechat_api/core/exceptions.py
ecjtu_wechat_api/models/__init__.py
ecjtu_wechat_api/models/course.py
ecjtu_wechat_api/models/exam.py
ecjtu_wechat_api/models/score.py
ecjtu_wechat_api/services/__init__.py
ecjtu_wechat_api/services/parse_course.py
ecjtu_wechat_api/services/parse_exam.py
ecjtu_wechat_api/services/parse_score.py
ecjtu_wechat_api/utils/__init__.py
ecjtu_wechat_api/utils/http.py
ecjtu_wechat_api/utils/logger.py
ecjtu_wechat_api/utils/persistence.py
ecjtu_wechat_api-1.1.0.dist-info/METADATA
ecjtu_wechat_api-1.1.0.dist-info/WHEEL
ecjtu_wechat_api-1.1.0.dist-info/licenses/LICENSE
ecjtu_wechat_api-1.1.0.dist-info/RECORD
