Metadata-Version: 2.4
Name: ecjtu-wechat-api
Version: 1.1.0
Summary: 华东交通大学教务系统微信版 API
Project-URL: Homepage, https://github.com/mochenya/ecjtu-wechat-api
Project-URL: Issues, https://github.com/mochenya/ecjtu-wechat-api/issues
Author: mochenya
License-Expression: MIT
License-File: LICENSE
Requires-Python: >=3.12
Requires-Dist: beautifulsoup4>=4.12.0
Requires-Dist: fastapi>=0.100.0
Requires-Dist: httpx>=0.24.0
Requires-Dist: pydantic>=2.0.0
Requires-Dist: python-dotenv>=1.0.0
Requires-Dist: uvicorn>=0.22.0
